pandas_helper/__init__.py
pandas_helper/data_summary.py
bharath_pandas_helper-0.1.dist-info/METADATA
bharath_pandas_helper-0.1.dist-info/WHEEL
bharath_pandas_helper-0.1.dist-info/top_level.txt
bharath_pandas_helper-0.1.dist-info/RECORD
