Metadata-Version: 2.4
Name: bharath_pandas_helper
Version: 0.1
Summary: A handy package to summarize datasets quickly
Author: BharathKumar
Author-email: bharath524419@gmail.com
Requires-Python: >=3.6
Requires-Dist: pandas
Dynamic: author
Dynamic: author-email
Dynamic: requires-dist
Dynamic: requires-python
Dynamic: summary
